dry_tests/__init__.py
dry_tests/apps.py
dry_tests/package.py
dry_tests/testcases.py
dry_tests/migrations/__init__.py
dry_tests/models/__init__.py
dry_tests/models/content.py
dry_tests/models/context.py
dry_tests/models/forms.py
dry_tests/models/requests.py
dry_tests/models/responses.py
dry_tests/models/urls.py
dry_tests/tests/__init__.py
dry_tests/tests/tests_models/__init__.py
dry_tests/tests/tests_models/test_urls.py
django_dry_tests-1.0.0.dist-info/LICENSE
django_dry_tests-1.0.0.dist-info/METADATA
django_dry_tests-1.0.0.dist-info/WHEEL
django_dry_tests-1.0.0.dist-info/top_level.txt
django_dry_tests-1.0.0.dist-info/RECORD
