Metadata-Version: 2.1
Name: django-dry-tests
Version: 1.0.0
Summary: Package with new powerful TestCases and Assets to test django application fast. TDD is supported
Home-page: https://github.com/quillcraftsman/django-dry-tests
Author: quillcraftsman
Author-email: quill@craftsman.lol
License: MIT
Project-URL: Documentation, https://drytest.craftsman.lol
Project-URL: Source, https://github.com/quillcraftsman/django-dry-tests
Project-URL: Tracker, https://github.com/quillcraftsman/django-dry-tests/issues
Project-URL: Release notes, https://github.com/quillcraftsman/django-dry-tests/releases
Project-URL: Changelog, https://github.com/quillcraftsman/django-dry-tests/releases
Project-URL: Download, https://pypi.org/project/django-dry-tests/
Keywords: django,tests,test-driven-development,asserts,testcases
Classifier: Development Status :: 4 - Beta
Classifier: Intended Audience :: Developers
Classifier: License :: OSI Approved :: MIT License
Classifier: Programming Language :: Python :: 3
Classifier: Environment :: Web Environment
Classifier: Framework :: Django
Classifier: Operating System :: OS Independent
Classifier: Topic :: Software Development :: Testing
Requires-Python: >=3
License-File: LICENSE
